[{"id":251187,"name":"Zonianá"},{"id":251250,"name":"Zarós"},{"id":251253,"name":"Zárkos"},{"id":251276,"name":"Nomós Zakýnthou"},{"id":251280,"name":"Zakynthos"},{"id":251283,"name":"Zacháro"},{"id":251292,"name":"Zagorá"},{"id":251297,"name":"Gýtheio"},{"id":251317,"name":"Yimnón"},{"id":251332,"name":"Giánnouli"},{"id":251366,"name":"Gérgeri"},{"id":251411,"name":"Geráki"},{"id":251465,"name":"Géfyra"},{"id":251525,"name":"Xylókastro"},{"id":251606,"name":"Vrontádos"},{"id":251667,"name":"Vravrona"},{"id":251681,"name":"Vrachnaíika"},{"id":251685,"name":"Vrakháti"},{"id":251773,"name":"Vouliagméni"},{"id":251780,"name":"Voúla"},{"id":251823,"name":"Vónitsa"},{"id":251833,"name":"Volos"},{"id":251851,"name":"Nomós Voiotías"},{"id":251888,"name":"Vlachópoulo"},{"id":251896,"name":"Vlachiótis"},{"id":251948,"name":"Výronas"},{"id":251959,"name":"Vília"},{"id":252030,"name":"Verdikoússa"},{"id":252062,"name":"Vélo"},{"id":252074,"name":"Velestíno"},{"id":252101,"name":"Vágia"},{"id":252164,"name":"Vathí"},{"id":252165,"name":"Vathý"},{"id":252166,"name":"Vathý"},{"id":252190,"name":"Vasilikón"},{"id":252200,"name":"Vasilikí"},{"id":252232,"name":"Varvásaina"},{"id":252239,"name":"Vartholomió"},{"id":252244,"name":"Varnávas"},{"id":252267,"name":"Vareiá"},{"id":252270,"name":"Vári"},{"id":252271,"name":"Vári"},{"id":252291,"name":"Várda"},{"id":252303,"name":"Vamvakoú"},{"id":252327,"name":"Valsamáta"},{"id":252486,"name":"Tsikalariá"},{"id":252523,"name":"Tsarítsani"},{"id":252601,"name":"Trípoli"},{"id":252626,"name":"Triovasálos"},{"id":252655,"name":"Tríkeri"},{"id":252661,"name":"Trikala"},{"id":252664,"name":"Tríkala"},{"id":252685,"name":"Ialysós"},{"id":252747,"name":"Traganón"},{"id":252750,"name":"Tragána"},{"id":252833,"name":"Tolón"},{"id":252848,"name":"Týrnavos"},{"id":252854,"name":"Tínos"},{"id":252862,"name":"Tympáki"},{"id":252864,"name":"Tílisos"},{"id":252889,"name":"Thrapsanón"},{"id":252891,"name":"Thouría"},{"id":252910,"name":"Thívai"},{"id":252920,"name":"Firá"},{"id":252927,"name":"Thymianá"},{"id":252939,"name":"Thesprotikó"},{"id":252941,"name":"Nomós Thesprotías"},{"id":252942,"name":"Thespiés"},{"id":252946,"name":"Thérmo"},{"id":252952,"name":"Thérissos"},{"id":252989,"name":"Terpsithéa"},{"id":253003,"name":"Témeni"},{"id":253045,"name":"Tanágra"},{"id":253075,"name":"Strovíki"},{"id":253130,"name":"Strátos"},{"id":253158,"name":"Steíri"},{"id":253164,"name":"Stýpsi"},{"id":253170,"name":"Stylída"},{"id":253218,"name":"Stefanovíkeio"},{"id":253286,"name":"Stános"},{"id":253302,"name":"Stamáta"},{"id":253305,"name":"Stalís"},{"id":253343,"name":"Lássi"},{"id":253356,"name":"Spétses"},{"id":253357,"name":"Sperchógeia"},{"id":253360,"name":"Spercheiáda"},{"id":253376,"name":"Spáta"},{"id":253394,"name":"Spárti"},{"id":253419,"name":"Soúrpi"},{"id":253420,"name":"Soúrmena"},{"id":253456,"name":"Soúda"},{"id":253494,"name":"Sofikón"},{"id":253581,"name":"Skópelos"},{"id":253582,"name":"Skópelos"},{"id":253614,"name":"Skýros"},{"id":253643,"name":"Skiáthos"},{"id":253666,"name":"Schísma Eloúndas"},{"id":253673,"name":"Schimatári"},{"id":253676,"name":"Skepastó"},{"id":253716,"name":"Skála Oropoú"},{"id":253717,"name":"Skalánion"},{"id":253739,"name":"Skála"},{"id":253759,"name":"Sitia"},{"id":253817,"name":"Synoikismós Chavaríou"},{"id":253858,"name":"Sými"},{"id":253866,"name":"Sylivainiótika"},{"id":253871,"name":"Sykoúrio"},{"id":253878,"name":"Sikyón"},{"id":253880,"name":"Síkinos"},{"id":253908,"name":"Sykiá"},{"id":253996,"name":"Sérifos"},{"id":254030,"name":"Selínia"},{"id":254032,"name":"Selianítika"},{"id":254045,"name":"Savália"},{"id":254064,"name":"Sardínia"},{"id":254112,"name":"Nomós Sámou"},{"id":254115,"name":"Samos"},{"id":254123,"name":"Sámi"},{"id":254144,"name":"Salamína"},{"id":254165,"name":"Royítika"},{"id":254170,"name":"Roviés"},{"id":254253,"name":"Rodotópi"},{"id":254283,"name":"Rizómylos"},{"id":254286,"name":"Rízoma"},{"id":254315,"name":"Río"},{"id":254352,"name":"Rethymno"},{"id":254353,"name":"Nomós Rethýmnis"},{"id":254425,"name":"Rafína"},{"id":254442,"name":"Pteleós"},{"id":254505,"name":"Psychikó"},{"id":254546,"name":"Psachná"},{"id":254584,"name":"Prokópi"},{"id":254599,"name":"Profítis Ilías"},{"id":254695,"name":"Nomós Prevézis"},{"id":254698,"name":"Préveza"},{"id":254746,"name":"Prámanta"},{"id":254842,"name":"Pórto Chéli"},{"id":254849,"name":"Portariá"},{"id":254864,"name":"Póros"},{"id":254865,"name":"Póros"},{"id":254898,"name":"Politiká"},{"id":254917,"name":"Polichnítos"},{"id":254949,"name":"Plomári"},{"id":254955,"name":"Pligónion"},{"id":254990,"name":"Platýkampos"},{"id":255013,"name":"Platariá"},{"id":255027,"name":"Plátanos Kalivíon"},{"id":255030,"name":"Plátanos"},{"id":255036,"name":"Plátanos"},{"id":255093,"name":"Plataiés"},{"id":255096,"name":"Plános"},{"id":255138,"name":"Pigí"},{"id":255161,"name":"Pithári"},{"id":255163,"name":"Pythagóreio"},{"id":255188,"name":"Pyrgíon"},{"id":255195,"name":"Pyrgetós"},{"id":255196,"name":"Pyrgetós"},{"id":255229,"name":"Pýrgos"},{"id":255242,"name":"Pýrgos"},{"id":255274,"name":"Piraeus"},{"id":255293,"name":"Pýlos"},{"id":255301,"name":"Pylí"},{"id":255305,"name":"Pýli"},{"id":255319,"name":"Pikérmi"},{"id":255377,"name":"Petroúpolis"},{"id":255398,"name":"Magoúla"},{"id":255439,"name":"Pétra"},{"id":255458,"name":"Péta"},{"id":255495,"name":"Periyiáli"},{"id":255498,"name":"Perivóli"},{"id":255507,"name":"Perivólia"},{"id":255524,"name":"Peristéri"},{"id":255562,"name":"Pérdika"},{"id":255585,"name":"Pérama"},{"id":255588,"name":"Pérama"},{"id":255589,"name":"Pérama"},{"id":255594,"name":"Perachóra"},{"id":255621,"name":"Pelópi"},{"id":255638,"name":"Pelasgía"},{"id":255646,"name":"Pediní"},{"id":255683,"name":"Pátra"},{"id":255689,"name":"Patitírion"},{"id":255709,"name":"Pásion"},{"id":255713,"name":"Pártira"},{"id":255718,"name":"Parthéni"},{"id":255721,"name":"Páros"},{"id":255736,"name":"Párga"},{"id":255739,"name":"Paravóla"},{"id":255750,"name":"Proástio"},{"id":255753,"name":"Parapótamos"},{"id":255760,"name":"Paramythiá"},{"id":255777,"name":"Paralía"},{"id":255798,"name":"Pappádos"},{"id":255807,"name":"Pappadátes"},{"id":255849,"name":"Pánormos"},{"id":255945,"name":"Panaitólion"},{"id":255959,"name":"Pámfila"},{"id":255971,"name":"Pallíni"},{"id":256047,"name":"Palamás"},{"id":256054,"name":"Pálairos"},{"id":256066,"name":"Palaiópyrgos"},{"id":256075,"name":"Palaió Fáliro"},{"id":256079,"name":"Palaiomonástiro"},{"id":256093,"name":"Palaiókipos"},{"id":256131,"name":"Palaióchora"},{"id":256155,"name":"Palekastro"},{"id":256173,"name":"Palaiá Fókaia"},{"id":256175,"name":"Palaiá Epídavros"},{"id":256197,"name":"Paianía"},{"id":256210,"name":"Oxílithos"},{"id":256223,"name":"Ovriá"},{"id":256257,"name":"Oropós"},{"id":256268,"name":"Orchomenós"},{"id":256284,"name":"Oreoí"},{"id":256296,"name":"Omvriakí"},{"id":256297,"name":"Omorfochóri"},{"id":256329,"name":"Oinoússes"},{"id":256339,"name":"Oinófyta"},{"id":256342,"name":"Papágou"},{"id":256428,"name":"Níkaia"},{"id":256429,"name":"Níkaia"},{"id":256449,"name":"Nerokoúros"},{"id":256485,"name":"Néon Monastírion"},{"id":256492,"name":"Néon Karlovásion"},{"id":256499,"name":"Neochorópoulo"},{"id":256504,"name":"Oichalía"},{"id":256508,"name":"Neochóri"},{"id":256509,"name":"Neochóri"},{"id":256520,"name":"Neochórion"},{"id":256527,"name":"Neochóri"},{"id":256554,"name":"Nénita"},{"id":256558,"name":"Neméa"},{"id":256571,"name":"Néa Tírins"},{"id":256572,"name":"Néa Stíra"},{"id":256574,"name":"Néa Smírni"},{"id":256575,"name":"Néa Smýrni"},{"id":256580,"name":"Néa Seléfkeia"},{"id":256589,"name":"Neápoli"},{"id":256592,"name":"Néa Péramos"},{"id":256593,"name":"Néa Palátia"},{"id":256596,"name":"Néa Manoláda"},{"id":256598,"name":"Néa Mákri"},{"id":256601,"name":"Ílion"},{"id":256606,"name":"Néa Kíos"},{"id":256614,"name":"Néa Ionía"},{"id":256621,"name":"Néa Filadélfeia"},{"id":256622,"name":"Néa Erythraía"},{"id":256626,"name":"Néa Artáki"},{"id":256627,"name":"Néa Anchiálos"},{"id":256632,"name":"Náxos"},{"id":256637,"name":"Náfplio"},{"id":256639,"name":"Náfpaktos"},{"id":256653,"name":"Náousa"},{"id":256660,"name":"Mouzourás"},{"id":256662,"name":"Mouzáki"},{"id":256664,"name":"Mouzaki"},{"id":256696,"name":"Mourniés"},{"id":256728,"name":"Moúlki"},{"id":256750,"name":"Moskháton"},{"id":256757,"name":"Mória"},{"id":256759,"name":"Morfovoúni"},{"id":256769,"name":"Monólithos"},{"id":256808,"name":"Monastiráki"},{"id":256824,"name":"Mólos"},{"id":256833,"name":"Moláoi"},{"id":256838,"name":"Mokhós"},{"id":256842,"name":"Moíres"},{"id":256860,"name":"Mitrópoli"},{"id":256865,"name":"Mytilinioí"},{"id":256866,"name":"Mytilene"},{"id":256872,"name":"Mytikas"},{"id":256879,"name":"Míthymna"},{"id":256883,"name":"Mitáta"},{"id":256914,"name":"Myrsíni"},{"id":256930,"name":"Mýrina"},{"id":256952,"name":"Mílos"},{"id":256968,"name":"Mýloi"},{"id":256985,"name":"Milésion"},{"id":257035,"name":"Mikrománi"},{"id":257056,"name":"Mykonos"},{"id":257080,"name":"Megísti"},{"id":257083,"name":"Metsovo"},{"id":257122,"name":"Methóni"},{"id":257126,"name":"Méthana"},{"id":257141,"name":"Metamórfosi Troizínos"},{"id":257149,"name":"Nomós Messinías"},{"id":257152,"name":"Messíni"},{"id":257186,"name":"Mesolóngi"},{"id":257224,"name":"Mesariá"},{"id":257243,"name":"Mertikaíika"},{"id":257258,"name":"Agía Triáda"},{"id":257268,"name":"Menídi"},{"id":257282,"name":"Melívoia"},{"id":257302,"name":"Melíssia"},{"id":257322,"name":"Meligalás"},{"id":257365,"name":"Mégara"},{"id":257395,"name":"Megalópoli"},{"id":257400,"name":"Megálo Chorió"},{"id":257406,"name":"Megalochóri"},{"id":257434,"name":"Megáli Khóra"},{"id":257448,"name":"Megála Kalývia"},{"id":257535,"name":"Mavrommáti"},{"id":257621,"name":"Martínon"},{"id":257643,"name":"Marmárion"},{"id":257669,"name":"Markópoulo Oropoú"},{"id":257671,"name":"Markópoulo"},{"id":257717,"name":"Marathónas"},{"id":257721,"name":"Marathókampos"},{"id":257762,"name":"Manoláda"},{"id":257804,"name":"Mandráki"},{"id":257811,"name":"Mándra"},{"id":257814,"name":"Mantoúdi"},{"id":257827,"name":"Mantamádos"},{"id":257859,"name":"Mália"},{"id":257868,"name":"Malesína"},{"id":257923,"name":"Makrísia"},{"id":257936,"name":"Makrinítsa"},{"id":257948,"name":"Makrychóri"},{"id":257949,"name":"Makrychóri"},{"id":257975,"name":"Makrakómi"},{"id":258004,"name":"Magoúla"},{"id":258007,"name":"Magoúla"},{"id":258011,"name":"Magoúla"},{"id":258013,"name":"Nomós Magnisías"},{"id":258066,"name":"Loutráki"},{"id":258076,"name":"Loutrá"},{"id":258091,"name":"Loúros"},{"id":258108,"name":"Loukísia"},{"id":258175,"name":"Lixoúri"},{"id":258182,"name":"Livanátes"},{"id":258198,"name":"Livádia"},{"id":258241,"name":"Lithakiá"},{"id":258261,"name":"Leipsoí"},{"id":258306,"name":"Límni"},{"id":258312,"name":"Límnes"},{"id":258315,"name":"Limín Khersonísou"},{"id":258332,"name":"Lykóvrysi"},{"id":258377,"name":"Ligourión"},{"id":258427,"name":"Lefkímmi"},{"id":258438,"name":"Lefkáda"},{"id":258445,"name":"Lefkada"},{"id":258463,"name":"Livadeiá"},{"id":258465,"name":"Lesbos"},{"id":258497,"name":"Lepenoú"},{"id":258500,"name":"Leonídio"},{"id":258521,"name":"Lékhaio"},{"id":258522,"name":"Lechainá"},{"id":258543,"name":"Lávrio"},{"id":258569,"name":"Nomós Lasithíou"},{"id":258575,"name":"Nomós Larísis"},{"id":258576,"name":"Lárisa"},{"id":258577,"name":"Lárimna"},{"id":258584,"name":"Lápas"},{"id":258610,"name":"Lagkáda"},{"id":258620,"name":"Lamía"},{"id":258634,"name":"Lambírion"},{"id":258655,"name":"Lálas"},{"id":258657,"name":"Nomós Lakonías"},{"id":258672,"name":"Lakkí"},{"id":258744,"name":"Krousón"},{"id":258754,"name":"Krokeés"},{"id":258757,"name":"Taxiárches"},{"id":258759,"name":"Kritsá"},{"id":258793,"name":"Kryonéri"},{"id":258819,"name":"Kríkellos"},{"id":258842,"name":"Kréstena"},{"id":258873,"name":"Kranídi"},{"id":258882,"name":"Kraniá Elassónas"},{"id":258912,"name":"Kouvarás"},{"id":258949,"name":"Koutselió"},{"id":258998,"name":"Kouroúpi"},{"id":259229,"name":"Kostakioí"},{"id":259245,"name":"Kos"},{"id":259251,"name":"Koropí"},{"id":259265,"name":"Koróni"},{"id":259289,"name":"Kórinthos"},{"id":259290,"name":"Nomós Korinthías"},{"id":259292,"name":"Domvraína"},{"id":259452,"name":"Kompóti"},{"id":259508,"name":"Kolympári"},{"id":259537,"name":"Kokkónion"},{"id":259578,"name":"Kokkíni Cháni"},{"id":259595,"name":"Kokkári"},{"id":259618,"name":"Koilás"},{"id":259707,"name":"Kýthnos"},{"id":259710,"name":"Kýthira"},{"id":259718,"name":"Kíssamos"},{"id":259720,"name":"Kírra"},{"id":259730,"name":"Kyriáki"},{"id":259734,"name":"Kyrás Vrýsi"},{"id":259745,"name":"Kipséli"},{"id":259754,"name":"Kiprianós"},{"id":259782,"name":"Kyparissía"},{"id":259796,"name":"Kinéta"},{"id":259802,"name":"Kímolos"},{"id":259806,"name":"Kými"},{"id":259813,"name":"Kyllíni"},{"id":259819,"name":"Nomós Kykládon"},{"id":259824,"name":"Kifisiá"},{"id":259830,"name":"Kiáto"},{"id":259917,"name":"Chóra"},{"id":259919,"name":"Chóra"},{"id":259949,"name":"Cholargós"},{"id":259970,"name":"Chios"},{"id":259973,"name":"Chios"},{"id":259993,"name":"Khiliomódhi"},{"id":260037,"name":"Chávari"},{"id":260093,"name":"Chaniotis"},{"id":260096,"name":"Nomós Chaniás"},{"id":260114,"name":"Chaniá"},{"id":260128,"name":"Khalkoútsion"},{"id":260133,"name":"Chalkída"},{"id":260142,"name":"Chalkiádes"},{"id":260144,"name":"Chálki"},{"id":260145,"name":"Chálki"},{"id":260171,"name":"Chalandrítsa"},{"id":260172,"name":"Khalándrion"},{"id":260183,"name":"Chaïdári"},{"id":260204,"name":"Keratsíni"},{"id":260210,"name":"Keratéa"},{"id":260220,"name":"Kerasochóri"},{"id":260308,"name":"Kéfalos"},{"id":260310,"name":"Nomós Kefallinías"},{"id":260348,"name":"Kéa"},{"id":260379,"name":"Kavásila"},{"id":260420,"name":"Katsikás"},{"id":260451,"name":"Káto Vlasía"},{"id":260468,"name":"Katoúna"},{"id":260473,"name":"Káto Tithoréa"},{"id":260478,"name":"Káto Soúlion"},{"id":260506,"name":"Káto Patísia"},{"id":260531,"name":"Káto Mazaráki"},{"id":260542,"name":"Káto Lekhónia"},{"id":260567,"name":"Káto Chorió"},{"id":260604,"name":"Káto Glykóvrysi"},{"id":260629,"name":"Káto Ássos"},{"id":260630,"name":"Káto Asítai"},{"id":260644,"name":"Káto Achaḯa"},{"id":260674,"name":"Katastárion"},{"id":260705,"name":"Katákali"},{"id":260780,"name":"Kastráki"},{"id":260804,"name":"Kastélli"},{"id":260811,"name":"Kastélla"},{"id":260821,"name":"Kastaniótissa"},{"id":260886,"name":"Karpochóri"},{"id":260891,"name":"Karpenísi"},{"id":260895,"name":"Karpathos"},{"id":260897,"name":"Karpásion"},{"id":260935,"name":"Kárystos"},{"id":260956,"name":"Karyés"},{"id":260979,"name":"Karés Apokorrónou"},{"id":260987,"name":"Karditsomagoúla"},{"id":260988,"name":"Nomós Kardhítsas"},{"id":260989,"name":"Kardítsa"},{"id":261002,"name":"Kardamás"},{"id":261003,"name":"Kardámaina"},{"id":261039,"name":"Karátoula"},{"id":261132,"name":"Kaparéllion"},{"id":261133,"name":"Kapandríti"},{"id":261150,"name":"Kandíla"},{"id":261167,"name":"Kanaláki"},{"id":261169,"name":"Kanália"},{"id":261211,"name":"Kaména Voúrla"},{"id":261242,"name":"Kampí"},{"id":261259,"name":"Kamári"},{"id":261263,"name":"Kamárion"},{"id":261283,"name":"Kamárai"},{"id":261396,"name":"Kalloní"},{"id":261401,"name":"Kallíthiro"},{"id":261414,"name":"Kallithéa"},{"id":261431,"name":"Kallifóni"},{"id":261445,"name":"Kalývia Thorikoú"},{"id":261490,"name":"Kalivári"},{"id":261497,"name":"Kalýves"},{"id":261507,"name":"Kálymnos"},{"id":261537,"name":"Kalávryta"},{"id":261571,"name":"Kálamos"},{"id":261596,"name":"Kalamiá"},{"id":261601,"name":"Kalampáka"},{"id":261604,"name":"Kalamata"},{"id":261614,"name":"Álimos"},{"id":261678,"name":"Kaisarianí"},{"id":261680,"name":"Kainoúryion"},{"id":261681,"name":"Kainoúryion"},{"id":261702,"name":"Micsi"},{"id":261708,"name":"Itháki"},{"id":261714,"name":"Itéa"},{"id":261715,"name":"Itéa"},{"id":261720,"name":"Istiaía"},{"id":261721,"name":"Isthmía"},{"id":261723,"name":"Ystérnia"},{"id":261741,"name":"Nomós Irakleíou"},{"id":261743,"name":"Irákleio"},{"id":261745,"name":"Irákleion"},{"id":261763,"name":"Ippoforvíon"},{"id":261772,"name":"Íos"},{"id":261777,"name":"Nomós Ioannínon"},{"id":261779,"name":"Ioánnina"},{"id":261797,"name":"Nomós Ileías"},{"id":261807,"name":"Igoumenítsa"},{"id":261814,"name":"Ierápetra"},{"id":261816,"name":"Ydroússa"},{"id":261822,"name":"Ýdra"},{"id":261842,"name":"Grizáno"},{"id":261895,"name":"Grammenítsa"},{"id":261900,"name":"Grammatikoú"},{"id":261903,"name":"Grammatikó"},{"id":261910,"name":"Gra Liyiá"},{"id":261912,"name":"Graikós"},{"id":261913,"name":"Graikochóri"},{"id":261921,"name":"Goúves"},{"id":261935,"name":"Goúrnes"},{"id":261941,"name":"Gouriá"},{"id":261956,"name":"Goúmero"},{"id":261996,"name":"Gónnoi"},{"id":262007,"name":"Gómfoi"},{"id":262036,"name":"Glyfáda"},{"id":262067,"name":"Gázi"},{"id":262091,"name":"Gavaloú"},{"id":262098,"name":"Gastoúni"},{"id":262104,"name":"Gargaliánoi"},{"id":262135,"name":"Galátsi"},{"id":262140,"name":"Galatás"},{"id":262143,"name":"Galatás"},{"id":262144,"name":"Galatás"},{"id":262159,"name":"Gaïtánion"},{"id":262187,"name":"Nomós Fthiótidos"},{"id":262217,"name":"Fry"},{"id":262319,"name":"Folégandros"},{"id":262322,"name":"Nomós Fokídos"},{"id":262383,"name":"Fyteíes"},{"id":262397,"name":"Filótion"},{"id":262402,"name":"Fílla"},{"id":262411,"name":"Filippiáda"},{"id":262418,"name":"Filiatrá"},{"id":262420,"name":"Filiátes"},{"id":262426,"name":"Fylí"},{"id":262433,"name":"Fíki"},{"id":262462,"name":"Fársala"},{"id":262465,"name":"Fáros"},{"id":262503,"name":"Magoúla"},{"id":262525,"name":"Fálanna"},{"id":262558,"name":"Examília"},{"id":262564,"name":"Nomós Evvoías"},{"id":262572,"name":"Nomós Evrytanías"},{"id":262603,"name":"Ermoúpolis"},{"id":262607,"name":"Ermióni"},{"id":262609,"name":"Erythrés"},{"id":262628,"name":"Erétria"},{"id":262629,"name":"Eresós"},{"id":262636,"name":"Epitálio"},{"id":262683,"name":"Ano Arhanes"},{"id":262687,"name":"Enipiás"},{"id":262696,"name":"Emporeío"},{"id":262698,"name":"Émponas"},{"id":262719,"name":"Ellinikó"},{"id":262752,"name":"Elefsína"},{"id":262757,"name":"Eleoúsa"},{"id":262776,"name":"Eláteia"},{"id":262784,"name":"Elassóna"},{"id":262833,"name":"Ekáli"},{"id":262862,"name":"Voulgaréli"},{"id":262920,"name":"Drépanon"},{"id":262969,"name":"Dhráfi"},{"id":263000,"name":"Domokós"},{"id":263020,"name":"Dodóni"},{"id":263021,"name":"Dodecanese"},{"id":263034,"name":"Dístomo"},{"id":263075,"name":"Dimitsána"},{"id":263166,"name":"Deskáti"},{"id":263178,"name":"Dhervéni"},{"id":263219,"name":"Delphi"},{"id":263257,"name":"Darátsos"},{"id":263471,"name":"Bendevís"},{"id":263535,"name":"Rodópoli"},{"id":263544,"name":"Báfra"},{"id":263646,"name":"Ágios Geórgios"},{"id":263698,"name":"Áyios Vasílios"},{"id":263714,"name":"Áyios Thomás"},{"id":263725,"name":"Ágios Stéfanos"},{"id":263730,"name":"Ágios Spyrídon"},{"id":263751,"name":"Áyios Serafím"},{"id":263805,"name":"Áyios Nikólaos"},{"id":263809,"name":"Arkoúdi"},{"id":263824,"name":"Ágios Nikólaos"},{"id":263854,"name":"Áyios Konstandínos"},{"id":263870,"name":"Agios Kirykos"},{"id":263897,"name":"Ágios Ioánnis"},{"id":263978,"name":"Agios Dimitrios"},{"id":263986,"name":"Agios Dimitrios"},{"id":263997,"name":"Áyios Athanásios"},{"id":264022,"name":"Ágios Andréas"},{"id":264083,"name":"Ágioi Déka"},{"id":264111,"name":"Agía Varvára"},{"id":264114,"name":"Agía Varvára"},{"id":264128,"name":"Agía Triáda"},{"id":264146,"name":"Agiásos"},{"id":264181,"name":"Agía Paraskeví"},{"id":264194,"name":"Agía Paraskeví"},{"id":264220,"name":"Ayía Marína"},{"id":264221,"name":"Agía Marína"},{"id":264223,"name":"Agía Marína"},{"id":264260,"name":"Agía Galíni"},{"id":264283,"name":"Agiá"},{"id":264353,"name":"Nomós Attikís"},{"id":264359,"name":"Atsipópoulo"},{"id":264371,"name":"Athens"},{"id":264374,"name":"Athíkia"},{"id":264390,"name":"Atalánti"},{"id":264396,"name":"Ástros"},{"id":264408,"name":"Astypálaia"},{"id":264416,"name":"Astakós"},{"id":264421,"name":"Ássos"},{"id":264445,"name":"Asprópyrgos"},{"id":264481,"name":"Asopós"},{"id":264482,"name":"Asopía"},{"id":264496,"name":"Asíni"},{"id":264501,"name":"Asímion"},{"id":264516,"name":"Argyroúpoli"},{"id":264519,"name":"Argyropoúli"},{"id":264545,"name":"Nomós Ártas"},{"id":264547,"name":"Artesianó"},{"id":264559,"name":"Árta"},{"id":264604,"name":"Árma"},{"id":264618,"name":"Archontochóri"},{"id":264637,"name":"Archaía Olympía"},{"id":264638,"name":"Arkhaía Kórinthos"},{"id":264641,"name":"Arkása"},{"id":264642,"name":"Arkalochóri"},{"id":264644,"name":"Nomós Arkadías"},{"id":264650,"name":"Áris"},{"id":264662,"name":"Aria"},{"id":264668,"name":"Argostólion"},{"id":264670,"name":"Árgos"},{"id":264673,"name":"Nomós Argolídos"},{"id":264677,"name":"Argalastí"},{"id":264679,"name":"Arfará"},{"id":264694,"name":"Áraxos"},{"id":264714,"name":"Aráchova"},{"id":264748,"name":"Apollonía"},{"id":264793,"name":"Anthíli"},{"id":264806,"name":"Anógeia"},{"id":264839,"name":"Áno Sýros"},{"id":264878,"name":"Áno Merá"},{"id":264888,"name":"Áno Liósia"},{"id":264890,"name":"Áno Lekhónia"},{"id":264897,"name":"Kopanáki"},{"id":264909,"name":"Áno Kastrítsi"},{"id":264928,"name":"Áno Kalentíni"},{"id":264929,"name":"Anoixi"},{"id":265001,"name":"Megalochóri"},{"id":265007,"name":"Agkídia"},{"id":265013,"name":"Angelókastro"},{"id":265028,"name":"Anéza"},{"id":265040,"name":"Andros"},{"id":265056,"name":"Andravída"},{"id":265075,"name":"Antíparos"},{"id":265078,"name":"Antimácheia"},{"id":265095,"name":"Anávra"},{"id":265096,"name":"Anávra"},{"id":265100,"name":"Anávyssos"},{"id":265107,"name":"Anatolí"},{"id":265127,"name":"Paralía Milátou"},{"id":265133,"name":"Anáfi"},{"id":265142,"name":"Amorgós"},{"id":265187,"name":"Ámfissa"},{"id":265189,"name":"Amfilochía"},{"id":265191,"name":"Amfíkleia"},{"id":265206,"name":"Ampelóna"},{"id":265210,"name":"Ambelókipoi"},{"id":265240,"name":"Ampelákia"},{"id":265243,"name":"Maroúsi"},{"id":265245,"name":"Amárynthos"},{"id":265252,"name":"Amaliáda"},{"id":265292,"name":"Almyrós"},{"id":265300,"name":"Álli Meriá"},{"id":265309,"name":"Alivéri"},{"id":265342,"name":"Alíartos"},{"id":265344,"name":"Alfeioúsa"},{"id":265417,"name":"Akráta"},{"id":265420,"name":"Akraifnía"},{"id":265488,"name":"Acharnés"},{"id":265491,"name":"Nomós Achaḯas"},{"id":265498,"name":"Aíyira"},{"id":265500,"name":"Aígio"},{"id":265502,"name":"Aegina"},{"id":265507,"name":"Aitolikó"},{"id":265508,"name":"Nomós Aitolías kai Akarnanías"},{"id":265533,"name":"Aigáleo"},{"id":265546,"name":"Aiánteio"},{"id":265560,"name":"Agrínio"},{"id":265601,"name":"Agriá"},{"id":265627,"name":"Agnanteró"},{"id":265650,"name":"Afrátion"},{"id":265711,"name":"Adámas"},{"id":390903,"name":"Hellenic Republic"},{"id":400666,"name":"Ródos"},{"id":406101,"name":"Nomós Piraiós"},{"id":408628,"name":"Néa Alikarnassós"},{"id":408684,"name":"Kremastí"},{"id":408685,"name":"Afántou"},{"id":408686,"name":"Archángelos"},{"id":408687,"name":"Líndos"},{"id":408689,"name":"Lárdos"},{"id":443460,"name":"Potokáki"},{"id":444350,"name":"Zipári"},{"id":444637,"name":"Lalódentra"},{"id":445298,"name":"Néos Oropós"},{"id":445406,"name":"Nomarchía Anatolikís Attikís"},{"id":445407,"name":"Nomarchía Dytikís Attikís"},{"id":445408,"name":"Nomarchía Athínas"},{"id":733749,"name":"Zygós"},{"id":733768,"name":"Akrolímni"},{"id":733776,"name":"Giannitsá"},{"id":733791,"name":"Gerakaroú"},{"id":733797,"name":"Yeorgoulás"},{"id":733798,"name":"Genisséa"},{"id":733802,"name":"Géfyra"},{"id":733818,"name":"Xiropótamos"},{"id":733827,"name":"Xinó Neró"},{"id":733828,"name":"Xilópolis"},{"id":733831,"name":"Xylaganí"},{"id":733839,"name":"Nomós Xánthis"},{"id":733840,"name":"Xánthi"},{"id":733842,"name":"Vrontoú"},{"id":733877,"name":"Vólakas"},{"id":733901,"name":"Vergína"},{"id":733902,"name":"Vérgi"},{"id":733905,"name":"Véroia"},{"id":733911,"name":"Velventós"},{"id":733933,"name":"Vathýlakkos"},{"id":733941,"name":"Vasiliká"},{"id":733955,"name":"Vamvakófyto"},{"id":733959,"name":"Valtotópi"},{"id":733965,"name":"Valteró"},{"id":733986,"name":"Tsotíli"},{"id":734003,"name":"Tsákoi"},{"id":734014,"name":"Trílofos"},{"id":734018,"name":"Tríkala"},{"id":734061,"name":"Tycheró"},{"id":734075,"name":"Nomós Thessaloníkis"},{"id":734077,"name":"Thessaloníki"},{"id":734080,"name":"Thérmi"},{"id":734094,"name":"Thásos"},{"id":734102,"name":"Terpní"},{"id":734108,"name":"Taxiárchis"},{"id":734120,"name":"Svorónos"},{"id":734128,"name":"Strymonikó"},{"id":734133,"name":"Stratónion"},{"id":734150,"name":"Stavroúpoli"},{"id":734155,"name":"Stavrós"},{"id":734183,"name":"Sourotí"},{"id":734187,"name":"Souflí"},{"id":734195,"name":"Sosándra"},{"id":734198,"name":"Sochós"},{"id":734213,"name":"Skoútari"},{"id":734216,"name":"Skotoússa"},{"id":734235,"name":"Skýdra"},{"id":734256,"name":"Leptokaryá"},{"id":734268,"name":"Sitagroí"},{"id":734270,"name":"Sisamía"},{"id":734284,"name":"Síndos"},{"id":734299,"name":"Sykiá"},{"id":734301,"name":"Sykiés"},{"id":734310,"name":"Sidirókastro"},{"id":734315,"name":"Siátista"},{"id":734320,"name":"Sfendámi"},{"id":734324,"name":"Sevastianá"},{"id":734328,"name":"Sérvia"},{"id":734329,"name":"Nomós Serrón"},{"id":734330,"name":"Sérres"},{"id":734336,"name":"Sélero"},{"id":734339,"name":"Sárti"},{"id":734355,"name":"Sápes"},{"id":734359,"name":"Samothráki"},{"id":734374,"name":"Rodópoli"},{"id":734375,"name":"Nomós Rodópis"},{"id":734385,"name":"Rizó"},{"id":734386,"name":"Rizómata"},{"id":734389,"name":"Rízia"},{"id":734391,"name":"Rizári"},{"id":734396,"name":"Ritíni"},{"id":734405,"name":"Péfka"},{"id":734426,"name":"Ptolemaḯda"},{"id":734430,"name":"Fteliá"},{"id":734436,"name":"Psychikó"},{"id":734440,"name":"Provatás"},{"id":734443,"name":"Próti"},{"id":734447,"name":"Prosotsáni"},{"id":734454,"name":"Prómachoi"},{"id":734455,"name":"Próchoma"},{"id":734461,"name":"Profítis Ilías"},{"id":734496,"name":"Potamiá"},{"id":734499,"name":"Portariá"},{"id":734517,"name":"Polýgyros"},{"id":734537,"name":"Políkhronon"},{"id":734538,"name":"Políchni"},{"id":734540,"name":"Polýkastro"},{"id":734543,"name":"Polykárpi"},{"id":734564,"name":"Plagiári"},{"id":734575,"name":"Platý"},{"id":734579,"name":"Platanórevma"},{"id":734602,"name":"Pigés"},{"id":734622,"name":"Chalástra"},{"id":734643,"name":"Pylaía"},{"id":734649,"name":"Nomós Pierías"},{"id":734664,"name":"Petroússa"},{"id":734672,"name":"Petrochóri"},{"id":734676,"name":"Petraná"},{"id":734683,"name":"Peteinós"},{"id":734695,"name":"Peristerá"},{"id":734698,"name":"Perístasi"},{"id":734712,"name":"Peraía"},{"id":734715,"name":"Péplos"},{"id":734719,"name":"Pentápoli"},{"id":734720,"name":"Pentaplátano"},{"id":734722,"name":"Pentálofos"},{"id":734725,"name":"Nomós Péllis"},{"id":734726,"name":"Pélla"},{"id":734731,"name":"Pedinó"},{"id":734733,"name":"Patrída"},{"id":734753,"name":"Paranésti"},{"id":734757,"name":"Paralía"},{"id":734761,"name":"Pappagiánnis"},{"id":734771,"name":"Panórama"},{"id":734819,"name":"Axós"},{"id":734820,"name":"Palaiokómi"},{"id":734821,"name":"Palaiochóri"},{"id":734832,"name":"Palaífyto"},{"id":734843,"name":"Páchni"},{"id":734854,"name":"Ouranoupolis"},{"id":734868,"name":"Ormýlia"},{"id":734880,"name":"Orestiáda"},{"id":734883,"name":"Oraiókastro"},{"id":734906,"name":"Nisí"},{"id":734915,"name":"Nikókleia"},{"id":734919,"name":"Nikísiani"},{"id":734924,"name":"Nigríta"},{"id":734935,"name":"Néos Skopós"},{"id":734938,"name":"Néos Mylótopos"},{"id":734939,"name":"Néos Marmarás"},{"id":734943,"name":"Néo Soúli"},{"id":734946,"name":"Néo Rýsi"},{"id":734947,"name":"Néo Petrítsi"},{"id":734957,"name":"Néo Agionéri"},{"id":734958,"name":"Neochoroúda"},{"id":734960,"name":"Neochóri"},{"id":734962,"name":"Neochóri"},{"id":734973,"name":"Néoi Epivátes"},{"id":734977,"name":"Néa Zíchni"},{"id":734978,"name":"Néa Výssa"},{"id":734979,"name":"Néa Tríglia"},{"id":734987,"name":"Néa Sánta"},{"id":734990,"name":"Néa Poteídaia"},{"id":734992,"name":"Néa Plágia"},{"id":734994,"name":"Néa Péramos"},{"id":734995,"name":"Néa Pélla"},{"id":734996,"name":"Ólynthos"},{"id":735001,"name":"Néa Michanióna"},{"id":735002,"name":"Néa Mesimvría"},{"id":735003,"name":"Néa Málgara"},{"id":735004,"name":"Néa Magnisía"},{"id":735007,"name":"Néa Krómi"},{"id":735014,"name":"Néa Karváli"},{"id":735015,"name":"Néa Karyá"},{"id":735016,"name":"Néa Kallikráteia"},{"id":735017,"name":"Néa Iraklítsa"},{"id":735018,"name":"Néa Irákleia"},{"id":735021,"name":"Néa Fókaia"},{"id":735023,"name":"Néa Éfesos"},{"id":735025,"name":"Néa Apollonía"},{"id":735030,"name":"Náousa"},{"id":735034,"name":"Mousthéni"},{"id":735111,"name":"Mikrópolis"},{"id":735115,"name":"Mikró Monastíri"},{"id":735135,"name":"Mikrókampos"},{"id":735146,"name":"Mýki"},{"id":735178,"name":"Mesopotamía"},{"id":735196,"name":"Mesiméri"},{"id":735215,"name":"Meneméni"},{"id":735220,"name":"Melíti"},{"id":735231,"name":"Melissochóri"},{"id":735235,"name":"Melíki"},{"id":735251,"name":"Megálos Prínos"},{"id":735264,"name":"Megáli Panagía"},{"id":735277,"name":"Mavrovoúni"},{"id":735318,"name":"Marína"},{"id":735327,"name":"Maniákoi"},{"id":735338,"name":"Mándalo"},{"id":735342,"name":"Díon"},{"id":735347,"name":"Makrochóri"},{"id":735348,"name":"Makrýgialos"},{"id":735365,"name":"Loutrós"},{"id":735375,"name":"Lófos"},{"id":735390,"name":"Livádi"},{"id":735393,"name":"Livaderó"},{"id":735395,"name":"Livadáki"},{"id":735399,"name":"Litóchoro"},{"id":735400,"name":"Lití"},{"id":735418,"name":"Limenária"},{"id":735430,"name":"Lýkeio"},{"id":735434,"name":"Lianovérgi"},{"id":735472,"name":"Lagyná"},{"id":735474,"name":"Lávara"},{"id":735481,"name":"Lagkadás"},{"id":735490,"name":"Lákkoma"},{"id":735497,"name":"Lagós"},{"id":735521,"name":"Krókos"},{"id":735523,"name":"Krithiá"},{"id":735526,"name":"Kristóni"},{"id":735546,"name":"Krýa Vrýsi"},{"id":735562,"name":"Nomós Kozánis"},{"id":735563,"name":"Kozáni"},{"id":735581,"name":"Kouloúra"},{"id":735588,"name":"Koufália"},{"id":735612,"name":"Kormísta"},{"id":735613,"name":"Korisós"},{"id":735615,"name":"Korinós"},{"id":735620,"name":"Koryfí"},{"id":735630,"name":"Kopanós"},{"id":735636,"name":"Kónitsa"},{"id":735638,"name":"Kontariótissa"},{"id":735640,"name":"Komotiní"},{"id":735643,"name":"Komniná"},{"id":735651,"name":"Kolchikón"},{"id":735654,"name":"Kolindrós"},{"id":735661,"name":"Kokkinóchoma"},{"id":735674,"name":"Koímisi"},{"id":735679,"name":"Koíla"},{"id":735682,"name":"Kleítos"},{"id":735695,"name":"Kleidí"},{"id":735702,"name":"Kítros"},{"id":735714,"name":"Kýria"},{"id":735720,"name":"Kyprínos"},{"id":735731,"name":"Kimméria"},{"id":735732,"name":"Kýmina"},{"id":735735,"name":"Nomós Kilkís"},{"id":735736,"name":"Kilkís"},{"id":735747,"name":"Chrysoúpolis"},{"id":735749,"name":"Chrysó"},{"id":735750,"name":"Chrysochóri"},{"id":735751,"name":"Chrysochórafa"},{"id":735764,"name":"Chortiátis"},{"id":735769,"name":"Choristí"},{"id":735794,"name":"Charopó"},{"id":735803,"name":"Chalkidóna"},{"id":735804,"name":"Nomós Chalkidikís"},{"id":735813,"name":"Kerkíni"},{"id":735821,"name":"Keramotí"},{"id":735839,"name":"Kefalóvryso"},{"id":735852,"name":"Kavýli"},{"id":735856,"name":"Kavallári"},{"id":735857,"name":"Nomós Kaválas"},{"id":735861,"name":"Kavála"},{"id":735872,"name":"Káto Scholári"},{"id":735879,"name":"Káto Nevrokópi"},{"id":735881,"name":"Káto Miliá"},{"id":735886,"name":"Loutráki"},{"id":735888,"name":"Káto Lipochóri"},{"id":735902,"name":"Káto Kamíla"},{"id":735914,"name":"Kateríni"},{"id":735925,"name":"Nomós Kastoriás"},{"id":735927,"name":"Kastoria"},{"id":735930,"name":"Kastanoússa"},{"id":735938,"name":"Kastaniés"},{"id":735954,"name":"Karperí"},{"id":735960,"name":"Karítsa"},{"id":735961,"name":"Karyótissa"},{"id":735972,"name":"Karyes"},{"id":735975,"name":"Kardiá"},{"id":736014,"name":"Kampánis"},{"id":736017,"name":"Kamariótissa"},{"id":736024,"name":"Kalós Agrós"},{"id":736029,"name":"Kalochóri"},{"id":736034,"name":"Kallithéa"},{"id":736039,"name":"Kallithéa"},{"id":736049,"name":"Kallífytos"},{"id":736051,"name":"Kalí Vrýsi"},{"id":736056,"name":"Kalýves Polygýrou"},{"id":736058,"name":"Ágios Spyrídon"},{"id":736065,"name":"Kalývia"},{"id":736067,"name":"Prínos"},{"id":736071,"name":"Kalí"},{"id":736082,"name":"Kalampáki"},{"id":736083,"name":"Kalamariá"},{"id":736102,"name":"Léchovo"},{"id":736120,"name":"Nomós Imathías"},{"id":736130,"name":"Ierissós"},{"id":736137,"name":"Íasmos"},{"id":736149,"name":"Nomós Grevenón"},{"id":736151,"name":"Grevená"},{"id":736166,"name":"Gouménissa"},{"id":736192,"name":"Gázoros"},{"id":736199,"name":"Gallikós"},{"id":736207,"name":"Galátista"},{"id":736208,"name":"Galatiní"},{"id":736210,"name":"Galatádes"},{"id":736222,"name":"Fotolívos"},{"id":736226,"name":"Néa Flogitá"},{"id":736228,"name":"Nomós Florínis"},{"id":736229,"name":"Flórina"},{"id":736243,"name":"Filótas"},{"id":736244,"name":"Fillýra"},{"id":736245,"name":"Fíliro"},{"id":736261,"name":"Féres"},{"id":736281,"name":"Exochí"},{"id":736283,"name":"Exaplátanos"},{"id":736287,"name":"Nomós Évrou"},{"id":736288,"name":"Evropós"},{"id":736291,"name":"Évosmos"},{"id":736296,"name":"Efkarpía"},{"id":736309,"name":"Erátyra"},{"id":736316,"name":"Episkopí"},{"id":736319,"name":"Epanomí"},{"id":736323,"name":"Emmanouíl Pappás"},{"id":736324,"name":"Empório"},{"id":736330,"name":"Eleftheroúpolis"},{"id":736336,"name":"Elefthério - Kordelió"},{"id":736346,"name":"Elaiochóri"},{"id":736354,"name":"Echínos"},{"id":736357,"name":"Édessa"},{"id":736363,"name":"Nomós Drámas"},{"id":736364,"name":"Dráma"},{"id":736381,"name":"Drosáto"},{"id":736386,"name":"Drymós"},{"id":736447,"name":"Didymóteicho"},{"id":736449,"name":"Diavatós"},{"id":736450,"name":"Diavatá"},{"id":736466,"name":"Dáto"},{"id":736581,"name":"Ágios Geórgios"},{"id":736586,"name":"Ágios Vasíleios"},{"id":736592,"name":"Ágios Pétros"},{"id":736598,"name":"Ágios Nikólaos"},{"id":736601,"name":"Ágios Mámas"},{"id":736602,"name":"Ágios Loukás"},{"id":736618,"name":"Ágios Athanásios"},{"id":736621,"name":"Ágios Athanásios"},{"id":736638,"name":"Agía Triáda"},{"id":736643,"name":"Agíasma"},{"id":736650,"name":"Agía Paraskeví"},{"id":736661,"name":"Axioúpoli"},{"id":736677,"name":"Ávato"},{"id":736682,"name":"Áthyra"},{"id":736687,"name":"Asvestochóri"},{"id":736692,"name":"Ássiros"},{"id":736694,"name":"Asproválta"},{"id":736716,"name":"Askós"},{"id":736725,"name":"Arsénio"},{"id":736727,"name":"Arrianá"},{"id":736732,"name":"Árnissa"},{"id":736733,"name":"Arnaía"},{"id":736735,"name":"Armenokhórion"},{"id":736751,"name":"Arísvi"},{"id":736753,"name":"Aridaía"},{"id":736754,"name":"Argos Orestiko"},{"id":736762,"name":"Aravissós"},{"id":736763,"name":"Áratos"},{"id":736767,"name":"Ápsalos"},{"id":736771,"name":"Apalós"},{"id":736792,"name":"Áno Poróïa"},{"id":736810,"name":"Áno Kómi"},{"id":736840,"name":"Ágkistro"},{"id":736843,"name":"Angelochóri"},{"id":736847,"name":"Agkathiá"},{"id":736859,"name":"Anatolikó"},{"id":736866,"name":"Anaráchi"},{"id":736878,"name":"Ammochóri"},{"id":736881,"name":"Amisianá"},{"id":736899,"name":"Ampelochóri"},{"id":736900,"name":"Ámpeloi"},{"id":736902,"name":"Ampeleíes"},{"id":736921,"name":"Alistráti"},{"id":736928,"name":"Alexandroupoli"},{"id":736929,"name":"Alexándreia"},{"id":736944,"name":"Akriní"},{"id":736964,"name":"Aigínio"},{"id":736971,"name":"Aianí"},{"id":736987,"name":"Áfytos"},{"id":737002,"name":"Ádendro"},{"id":865238,"name":"Eirinoúpoli"},{"id":865290,"name":"Ágios Pávlos"},{"id":865291,"name":"Triandría"},{"id":865331,"name":"Melíssi"},{"id":2463549,"name":"Virós"},{"id":2463568,"name":"Stratiá"},{"id":2463575,"name":"Sinarádes"},{"id":2463594,"name":"Potamós"},{"id":2463662,"name":"Kontokáli"},{"id":2463670,"name":"Kynopiástes"},{"id":2463676,"name":"Nomós Kerkýras"},{"id":2463679,"name":"Corfu"},{"id":2463692,"name":"Káto Korakiána"},{"id":2463701,"name":"Kassiopi"},{"id":2463705,"name":"Kanáli"},{"id":2463721,"name":"Gastoúri"},{"id":2463750,"name":"Benítses"},{"id":2463759,"name":"Ágios Rókkos"},{"id":2463763,"name":"Ágios Matthaíos"},{"id":2463771,"name":"Agía Eleoúsa"},{"id":2463800,"name":"Alepoú"},{"id":6295624,"name":"Villa Ritz"},{"id":6324534,"name":"Vrilissia"},{"id":6354951,"name":"Faliraki"},{"id":6544035,"name":"Young Inn"},{"id":6621623,"name":"Archipolis"},{"id":6639653,"name":"Alimos"},{"id":6692203,"name":"Agios Prokopios"},{"id":6692234,"name":"Potós"},{"id":6692632,"name":"Attica"},{"id":6692641,"name":"Agios Georgis"},{"id":6692661,"name":"Pefkochori"},{"id":6692709,"name":"Nidri"},{"id":6693122,"name":"Mesolongi"},{"id":6697800,"name":"Central Greece"},{"id":6697801,"name":"Central Macedonia"},{"id":6697802,"name":"Crete"},{"id":6697803,"name":"Eastern Macedonia and Thrace"},{"id":6697804,"name":"Epirus"},{"id":6697805,"name":"Ionian Islands"},{"id":6697806,"name":"North Aegean"},{"id":6697807,"name":"Peloponnese"},{"id":6697808,"name":"South Aegean"},{"id":6697809,"name":"Thessaly"},{"id":6697810,"name":"Western Greece"},{"id":6697811,"name":"Western Macedonia"},{"id":6779072,"name":"Néa Kríni"},{"id":6942763,"name":"Alyki"},{"id":6943434,"name":"Dimos Artas"},{"id":6951028,"name":"Aggeliká"},{"id":6951046,"name":"Tagkoú"},{"id":7290250,"name":"Agrilia"},{"id":7290409,"name":"Kefalonia"},{"id":7303595,"name":"Dimos Ioánnina"},{"id":7522530,"name":"Marousi"},{"id":7648744,"name":"Metaxourgio"},{"id":7667930,"name":"Ymittos"},{"id":7668056,"name":"Makry-Gialos"},{"id":7701425,"name":"Kambos"},{"id":7910877,"name":"Fanari"},{"id":8131587,"name":"Ymittos Athens"},{"id":8133665,"name":"Dimos Nea Smyrni"},{"id":8133666,"name":"Dimos Pavlos Melas"},{"id":8133667,"name":"Dimos Agios Dimitrios"},{"id":8133668,"name":"Dimos Tripoli"},{"id":8133669,"name":"Dimos Aigialeia"},{"id":8133670,"name":"Dimos Kalavryta"},{"id":8133671,"name":"Dimos West Achaea"},{"id":8133673,"name":"Dimos Corinth"},{"id":8133674,"name":"Dimos Nemea"},{"id":8133678,"name":"Dimos Neapoli-Sykies"},{"id":8133680,"name":"Dimos Filadelfeia-Chalkidona"},{"id":8133681,"name":"Dimos Milos"},{"id":8133682,"name":"Dimos Serifos"},{"id":8133683,"name":"Dimos Sifnos"},{"id":8133685,"name":"Dimos Pallini"},{"id":8133686,"name":"Dimos Rafina-Pikermi"},{"id":8133690,"name":"Dimos Patras"},{"id":8133691,"name":"Dimos Andravida-Kyllini"},{"id":8133694,"name":"Dimos Kifisia"},{"id":8133695,"name":"Chersonisos"},{"id":8133697,"name":"Dimos Naxos and Lesser Cyclades"},{"id":8133699,"name":"Dimos Paros"},{"id":8133700,"name":"Kastelorizo"},{"id":8133701,"name":"Dimos Aktio-Vonitsa"},{"id":8133702,"name":"Kythira"},{"id":8133704,"name":"Dimos Acharnes"},{"id":8133706,"name":"Dimos Missolonghi"},{"id":8133707,"name":"Dimos Nafpaktia"},{"id":8133709,"name":"Dimos Poros"},{"id":8133710,"name":"Dimos Dafni-Ymittos"},{"id":8133712,"name":"Dimos Ilida (Dimos Ilidas)"},{"id":8133716,"name":"Dimos Florina"},{"id":8133718,"name":"Dimos Sparti"},{"id":8133720,"name":"Dimos Dodoni"},{"id":8133722,"name":"Dimos Zitsa"},{"id":8133725,"name":"Dimos Igoumenitsa"},{"id":8133729,"name":"Dimos Chalcis"},{"id":8133731,"name":"Dimos Karpenisi"},{"id":8133738,"name":"Dimos Lamia"},{"id":8133743,"name":"Dimos Preveza"},{"id":8133744,"name":"Delphi"},{"id":8133746,"name":"Dimos Molos-Agios Konstantinos"},{"id":8133747,"name":"Ikaria"},{"id":8133749,"name":"Dimos Samos"},{"id":8133750,"name":"Dimos Apokoronas"},{"id":8133755,"name":"Dimos Lesbos"},{"id":8133757,"name":"Dimos Lemnos"},{"id":8133759,"name":"Dimos Rethymno"},{"id":8133760,"name":"Dimos Trifylia"},{"id":8133762,"name":"Chania"},{"id":8133764,"name":"Dimos Kozani"},{"id":8133766,"name":"Dimos Salaminas"},{"id":8133769,"name":"Dimos Hydra"},{"id":8133770,"name":"Dimos Marousi"},{"id":8133772,"name":"Dimos Spata-Artemida"},{"id":8133774,"name":"Dimos Pylaia-Chortiatis"},{"id":8133777,"name":"Dimos Piraeus"},{"id":8133778,"name":"Dimos Didymoteicho"},{"id":8133779,"name":"Dimos Alexandroupoli"},{"id":8133780,"name":"Dimos Nea Ionia"},{"id":8133781,"name":"Dimos Rhodes"},{"id":8133783,"name":"Dimos Peristeri"},{"id":8133785,"name":"Dimos Kileler"},{"id":8133786,"name":"Dimos Larissa"},{"id":8133791,"name":"Dimos Almyros"},{"id":8133795,"name":"Dimos Oraiokastro"},{"id":8133798,"name":"Dimos Galatsi"},{"id":8133800,"name":"Dimos North Kynouria"},{"id":8133802,"name":"Dimos Megalopoli"},{"id":8133804,"name":"Dimos Epidaurus"},{"id":8133806,"name":"Dimos Nafplio"},{"id":8133807,"name":"Dimos Vrilissia"},{"id":8133808,"name":"Dimos Fyli"},{"id":8133809,"name":"Dimos Nikaia-Agios Ioannis Rentis"},{"id":8133810,"name":"Dimos Minoa Pediada"},{"id":8133811,"name":"Dimos Astypalaia"},{"id":8133812,"name":"Dimos Kalymnos"},{"id":8133814,"name":"Dimos Leros"},{"id":8133821,"name":"Dimos Chios"},{"id":8133827,"name":"Dimos Komotini"},{"id":8133828,"name":"Dimos Agia Paraskevi"},{"id":8133830,"name":"Dimos Andros"},{"id":8133832,"name":"Dimos Santorini"},{"id":8133833,"name":"Dimos Ios"},{"id":8133837,"name":"Dimos Xanthi"},{"id":8133839,"name":"Dimos Papagou-Cholargos"},{"id":8133840,"name":"Dimos Penteli"},{"id":8133841,"name":"Dimos Thessaloniki"},{"id":8133842,"name":"Dimos Chalandri"},{"id":8133844,"name":"Dimos Trikala"},{"id":8133845,"name":"Dimos Agrinio"},{"id":8133846,"name":"Dimos Dio-Olympos"},{"id":8133847,"name":"Dimos Katerini"},{"id":8133848,"name":"Dimos Pella"},{"id":8133850,"name":"Dimos Kefalonia"},{"id":8133851,"name":"Dimos Lefkada"},{"id":8133854,"name":"Dimos Zakynthos"},{"id":8133855,"name":"Dimos Corfu"},{"id":8133857,"name":"Dimos Eordaia"},{"id":8133858,"name":"Dimos Deskati"},{"id":8133860,"name":"Dimos Orestida"},{"id":8133863,"name":"Dimos Visaltia"},{"id":8133864,"name":"Dimos Irakleia"},{"id":8133866,"name":"Dimos Serres"},{"id":8133867,"name":"Dimos Sintiki"},{"id":8133868,"name":"Dimos Aristotelis"},{"id":8133876,"name":"Dimos Athens"},{"id":8133877,"name":"Dimos Zografos"},{"id":8133878,"name":"Dimos Nestos"},{"id":8133880,"name":"Dimos Kallithea"},{"id":8133882,"name":"Dimos Naousa"},{"id":8133883,"name":"Dimos Elefsina"},{"id":8133884,"name":"Dimos Mandra-Eidyllia"},{"id":8133885,"name":"Dimos Megara"},{"id":8133886,"name":"Dimos Glyfada"},{"id":8133887,"name":"Dimos Pyrgos"},{"id":8133888,"name":"Dimos Metamorfosi"},{"id":8133892,"name":"Dimos Drama"},{"id":8133894,"name":"Dimos Volos"},{"id":8133898,"name":"Thasos"},{"id":8133899,"name":"Dimos Kavala"},{"id":8133900,"name":"Dimos Orestiada"},{"id":8133902,"name":"Dimos Eretria"},{"id":8133903,"name":"Dimos Istiaia-Aidipsos"},{"id":8133904,"name":"Dimos Karystos"},{"id":8133908,"name":"Dimos Thebes"},{"id":8133909,"name":"Dimos Livadeia"},{"id":8133910,"name":"Dimos Orchomenos"},{"id":8133912,"name":"Dimos Edessa"},{"id":8133914,"name":"Dimos Tanagra"},{"id":8133915,"name":"Dimos Volvi"},{"id":8133916,"name":"Dimos Delta"},{"id":8133917,"name":"Dimos Thermaikos"},{"id":8133918,"name":"Dimos Kordelio-Evosmos"},{"id":8133919,"name":"Dimos Ilio"},{"id":8133920,"name":"Dimos Heraklion"},{"id":8133921,"name":"Dimos Dionysos"},{"id":8133922,"name":"Dimos Kropia"},{"id":8133923,"name":"Dimos Lavreotiki"},{"id":8133926,"name":"Dimos Petroupoli"},{"id":8133927,"name":"Dimos Syros-Ermoupoli"},{"id":8133928,"name":"Dimos Tinos"},{"id":8133930,"name":"Dimos Ierapetra"},{"id":8133932,"name":"Dimos Veroia"},{"id":8133933,"name":"Dimos Mykonos"},{"id":8133934,"name":"Dimos Amorgos"},{"id":8133939,"name":"Dimos Skiathos"},{"id":8133942,"name":"Dimos Kalampaka"},{"id":8133946,"name":"Dimos Vari-Voula-Vouliagmeni"},{"id":8133947,"name":"Dimos Markopoulo Mesogaias"},{"id":8133948,"name":"Dimos Siteia"},{"id":8133951,"name":"Dimos Alimos"},{"id":8133952,"name":"Dimos Kea"},{"id":8133953,"name":"Dimos Kythnos"},{"id":8133955,"name":"Dimos Karpathos"},{"id":8133956,"name":"Dimos Kasos"},{"id":8133957,"name":"Dimos Kos"},{"id":8133959,"name":"Dimos Kalamaria"},{"id":8133960,"name":"Dimos Palaio Faliro"},{"id":8133961,"name":"Dimos Aspropyrgos"},{"id":8133962,"name":"Dimos Polygyros"},{"id":8133965,"name":"Dimos Keratsini-Drapetsona"},{"id":8133966,"name":"Dimos Kastoria"},{"id":8133969,"name":"Dimos Kilkis"},{"id":8133970,"name":"Dimos Paionia"},{"id":8133971,"name":"Dimos Kalamata"},{"id":8133973,"name":"Dimos Aigaleo"},{"id":8133974,"name":"Dimos Perama"},{"id":8133975,"name":"Dimos Skyros"},{"id":8133976,"name":"Dimos Grevena"},{"id":8133977,"name":"Dimos Loutraki-Agioi Theodoroi"},{"id":8133978,"name":"Dimos Xylokastro-Evrostina"},{"id":8133979,"name":"Dimos Argos-Mykines"},{"id":8133982,"name":"Dimos Elliniko-Argyroupoli"},{"id":8133984,"name":"Dimos Karditsa"},{"id":8133985,"name":"Dimos Ampelokipoi-Menemeni"},{"id":8133987,"name":"Dimos Oichalia"},{"id":8133988,"name":"Dimos Pylos-Nestoras"},{"id":8145341,"name":"Vagiés"},{"id":8200697,"name":"Asklipieío"},{"id":8201845,"name":"Gérakas"},{"id":8202413,"name":"Megálo Chorió"},{"id":8223990,"name":"Kolonaki"}]