[{"id":2959959,"name":"Wormeldange"},{"id":2959961,"name":"Wolwelange"},{"id":2959964,"name":"Wolpert"},{"id":2959966,"name":"Wollefsmillen"},{"id":2959967,"name":"Wintrange"},{"id":2959968,"name":"Winseler"},{"id":2959971,"name":"Wincrange"},{"id":2959972,"name":"Wilwerwiltz"},{"id":2959973,"name":"Wilwerdange"},{"id":2959975,"name":"Wiltz"},{"id":2959977,"name":"Wiltz"},{"id":2959978,"name":"Wiltz"},{"id":2959980,"name":"Wickrange"},{"id":2959982,"name":"Weyer"},{"id":2959983,"name":"Wemperhardt"},{"id":2959984,"name":"Welsdorf"},{"id":2959985,"name":"Welscheid"},{"id":2959987,"name":"Wellenstein"},{"id":2959988,"name":"Welfrange"},{"id":2959989,"name":"Weiswampach"},{"id":2959993,"name":"Weimershof"},{"id":2959995,"name":"Weiler"},{"id":2959996,"name":"Weiler-la-Tour"},{"id":2959997,"name":"Weilerbach"},{"id":2960000,"name":"Weidingen"},{"id":2960002,"name":"Weicherdange"},{"id":2960003,"name":"Wecker"},{"id":2960006,"name":"Watrange"},{"id":2960007,"name":"Wasserbillig"},{"id":2960008,"name":"Warken"},{"id":2960010,"name":"Walferdange"},{"id":2960011,"name":"Walsdorf"},{"id":2960013,"name":"Waldbredimus"},{"id":2960014,"name":"Waldbillig"},{"id":2960016,"name":"Wahlhausen"},{"id":2960017,"name":"Wahl"},{"id":2960019,"name":"Vichten"},{"id":2960020,"name":"Vianden"},{"id":2960021,"name":"Vianden"},{"id":2960022,"name":"Useldange"},{"id":2960023,"name":"Urspelt"},{"id":2960026,"name":"Uebersyren"},{"id":2960027,"name":"Tuntange"},{"id":2960030,"name":"Troisvierges"},{"id":2960031,"name":"Troisvierges"},{"id":2960033,"name":"Troine"},{"id":2960034,"name":"Trintange"},{"id":2960035,"name":"Pommerloch"},{"id":2960042,"name":"Tétange"},{"id":2960044,"name":"Tarchamps"},{"id":2960045,"name":"Tandel"},{"id":2960046,"name":"Tadler"},{"id":2960047,"name":"Syren"},{"id":2960050,"name":"Surré"},{"id":2960054,"name":"Strassen"},{"id":2960055,"name":"Stolzembourg"},{"id":2960056,"name":"Stockem"},{"id":2960058,"name":"Steinsel"},{"id":2960061,"name":"Steinfort"},{"id":2960062,"name":"Stegen"},{"id":2960063,"name":"Stadtbredimus"},{"id":2960067,"name":"Soleuvre"},{"id":2960068,"name":"Siebenaler"},{"id":2960070,"name":"Septfontaines"},{"id":2960072,"name":"Senningen"},{"id":2960082,"name":"Schuttrange"},{"id":2960083,"name":"Schrondweiler"},{"id":2960084,"name":"Schrassig"},{"id":2960085,"name":"Schouweiler"},{"id":2960088,"name":"Schoos"},{"id":2960089,"name":"Schoenfels"},{"id":2960094,"name":"Schlindermanderscheid"},{"id":2960102,"name":"Schifflange"},{"id":2960103,"name":"Schifflange"},{"id":2960104,"name":"Schieren"},{"id":2960107,"name":"Schengen"},{"id":2960108,"name":"Scheidgen"},{"id":2960109,"name":"Scheidel"},{"id":2960111,"name":"Schandel"},{"id":2960112,"name":"Savelborn"},{"id":2960114,"name":"Sassel"},{"id":2960115,"name":"Sanem"},{"id":2960117,"name":"Sandweiler"},{"id":2960120,"name":"Saeul"},{"id":2960123,"name":"Rumelange"},{"id":2960124,"name":"Rumelange"},{"id":2960126,"name":"Roost"},{"id":2960127,"name":"Rosport"},{"id":2960128,"name":"Roodt-sur-Syre"},{"id":2960130,"name":"Roodt"},{"id":2960133,"name":"Rollingen"},{"id":2960135,"name":"Roeser"},{"id":2960136,"name":"Roedt"},{"id":2960137,"name":"Roedgen"},{"id":2960139,"name":"Rodershausen"},{"id":2960140,"name":"Roder"},{"id":2960141,"name":"Rodenbourg"},{"id":2960143,"name":"Rodange"},{"id":2960144,"name":"Rippweiler"},{"id":2960145,"name":"Rippig"},{"id":2960149,"name":"Reuler"},{"id":2960150,"name":"Reuland"},{"id":2960152,"name":"Remich"},{"id":2960154,"name":"Remich"},{"id":2960155,"name":"Remerschen"},{"id":2960156,"name":"Reisdorf"},{"id":2960157,"name":"Reimberg"},{"id":2960158,"name":"Reichlange"},{"id":2960160,"name":"Redange-sur-Attert"},{"id":2960161,"name":"Redange"},{"id":2960164,"name":"Reckange-sur-Mess"},{"id":2960165,"name":"Reckange"},{"id":2960166,"name":"Rameldange"},{"id":2960167,"name":"Rambrouch"},{"id":2960168,"name":"Putscheid"},{"id":2960171,"name":"Pratz"},{"id":2960174,"name":"Pontpierre"},{"id":2960176,"name":"Platen"},{"id":2960178,"name":"Pissange"},{"id":2960180,"name":"Pintsch"},{"id":2960183,"name":"Pettingen"},{"id":2960185,"name":"Petit-Nobressart"},{"id":2960187,"name":"Pétange"},{"id":2960188,"name":"Pétange"},{"id":2960189,"name":"Perlé"},{"id":2960190,"name":"Peppange"},{"id":2960194,"name":"Osweiler"},{"id":2960195,"name":"Ospern"},{"id":2960197,"name":"Olm"},{"id":2960200,"name":"Oetrange"},{"id":2960201,"name":"Oberwampach"},{"id":2960205,"name":"Oberpallen"},{"id":2960207,"name":"Obercorn"},{"id":2960209,"name":"Oberfeulen"},{"id":2960211,"name":"Oberdonven"},{"id":2960212,"name":"Oberanven"},{"id":2960213,"name":"Nothum"},{"id":2960214,"name":"Nospelt"},{"id":2960216,"name":"Nommern"},{"id":2960217,"name":"Noertzange"},{"id":2960219,"name":"Noerdange"},{"id":2960221,"name":"Nocher"},{"id":2960223,"name":"Niederwampach"},{"id":2960226,"name":"Niederpallen"},{"id":2960228,"name":"Niedercorn"},{"id":2960231,"name":"Niederanven"},{"id":2960234,"name":"Neunhausen"},{"id":2960243,"name":"Neidhausen"},{"id":2960244,"name":"Nagem"},{"id":2960245,"name":"Nachtmanderscheid"},{"id":2960247,"name":"Munshausen"},{"id":2960250,"name":"Müllendorf"},{"id":2960252,"name":"Moutfort"},{"id":2960257,"name":"Mondorf-les-Bains"},{"id":2960258,"name":"Mondercange"},{"id":2960259,"name":"Mompach"},{"id":2960260,"name":"Moestroff"},{"id":2960261,"name":"Moesdorf"},{"id":2960262,"name":"Moersdorf"},{"id":2960266,"name":"Michelbouch"},{"id":2960267,"name":"Michelau"},{"id":2960270,"name":"Mertzig"},{"id":2960271,"name":"Mertert"},{"id":2960273,"name":"Merscheid"},{"id":2960275,"name":"Mersch"},{"id":2960276,"name":"Mersch"},{"id":2960278,"name":"Merkholz"},{"id":2960280,"name":"Mensdorf"},{"id":2960281,"name":"Meispelt"},{"id":2960282,"name":"Medingen"},{"id":2960283,"name":"Medernach"},{"id":2960285,"name":"Mecher"},{"id":2960288,"name":"Massen"},{"id":2960293,"name":"Marnach"},{"id":2960294,"name":"Marienthal"},{"id":2960296,"name":"Manternach"},{"id":2960299,"name":"Mamer"},{"id":2960312,"name":"Machtum"},{"id":2960313,"name":"Grand Duchy of Luxembourg"},{"id":2960314,"name":"District de Luxembourg"},{"id":2960315,"name":"Luxembourg"},{"id":2960316,"name":"Luxembourg"},{"id":2960318,"name":"Lultzhausen"},{"id":2960319,"name":"Lullange"},{"id":2960322,"name":"Lorentzweiler"},{"id":2960324,"name":"Longsdorf"},{"id":2960326,"name":"Livange"},{"id":2960327,"name":"Lipperscheid"},{"id":2960328,"name":"Lintgen"},{"id":2960329,"name":"Linger"},{"id":2960331,"name":"Limpach"},{"id":2960332,"name":"Lieler"},{"id":2960333,"name":"Liefrange"},{"id":2960335,"name":"Leudelange"},{"id":2960336,"name":"Lentzweiler"},{"id":2960337,"name":"Lenningen"},{"id":2960340,"name":"Lellingen"},{"id":2960342,"name":"Lellig"},{"id":2960343,"name":"Leithum"},{"id":2960350,"name":"Larochette"},{"id":2960352,"name":"Lannen"},{"id":2960358,"name":"Lamadelaine"},{"id":2960359,"name":"Kuborn"},{"id":2960363,"name":"Kopstal"},{"id":2960366,"name":"Koetschette"},{"id":2960367,"name":"Koerich"},{"id":2960370,"name":"Kockelscheuer"},{"id":2960372,"name":"Kobenbour"},{"id":2960373,"name":"Knaphoscheid"},{"id":2960378,"name":"Kleinbettingen"},{"id":2960387,"name":"Keispelt"},{"id":2960389,"name":"Kehlen"},{"id":2960391,"name":"Kayl"},{"id":2960392,"name":"Kayl"},{"id":2960393,"name":"Kautenbach"},{"id":2960394,"name":"Kaundorf"},{"id":2960399,"name":"Kahler"},{"id":2960400,"name":"Junglinster"},{"id":2960410,"name":"Itzig"},{"id":2960413,"name":"Insenborn"},{"id":2960414,"name":"Ingeldorf"},{"id":2960415,"name":"Imbringen"},{"id":2960417,"name":"Huttange"},{"id":2960418,"name":"Hupperdange"},{"id":2960420,"name":"Huncherange"},{"id":2960421,"name":"Huldange"},{"id":2960424,"name":"Hovelange"},{"id":2960427,"name":"Hostert"},{"id":2960429,"name":"Hosingen"},{"id":2960432,"name":"Hoscheid"},{"id":2960436,"name":"Holzthum"},{"id":2960437,"name":"Holzem"},{"id":2960438,"name":"Holtz"},{"id":2960441,"name":"Hollenfels"},{"id":2960447,"name":"Hoffelt"},{"id":2960450,"name":"Hoesdorf"},{"id":2960453,"name":"Hobscheid"},{"id":2960454,"name":"Hivange"},{"id":2960457,"name":"Hesperange"},{"id":2960467,"name":"Hemstal"},{"id":2960468,"name":"Helmsange"},{"id":2960469,"name":"Helmdange"},{"id":2960470,"name":"Hellange"},{"id":2960471,"name":"Heispelt"},{"id":2960472,"name":"Heisdorf"},{"id":2960475,"name":"Heinerscheid"},{"id":2960478,"name":"Heiderscheid"},{"id":2960481,"name":"Heffingen"},{"id":2960485,"name":"Hautcharage"},{"id":2960486,"name":"Hautbellain"},{"id":2960488,"name":"Hassel"},{"id":2960491,"name":"Harlange"},{"id":2960494,"name":"Hamiville"},{"id":2960497,"name":"Haller"},{"id":2960499,"name":"Hagelsdorf"},{"id":2960501,"name":"Hachiville"},{"id":2960504,"name":"Grundhof"},{"id":2960506,"name":"Grumelscheid"},{"id":2960510,"name":"Grosbous"},{"id":2960513,"name":"District de Grevenmacher"},{"id":2960514,"name":"Grevenmacher"},{"id":2960515,"name":"Grevenmacher"},{"id":2960517,"name":"Grevenknapp"},{"id":2960519,"name":"Grevels"},{"id":2960523,"name":"Greiveldange"},{"id":2960524,"name":"Greisch"},{"id":2960525,"name":"Graulinster"},{"id":2960531,"name":"Gosseldange"},{"id":2960532,"name":"Gonderange"},{"id":2960533,"name":"Goetzingen"},{"id":2960537,"name":"Goeblange"},{"id":2960539,"name":"Godbrange"},{"id":2960542,"name":"Girst"},{"id":2960543,"name":"Gilsdorf"},{"id":2960545,"name":"Geyershaff"},{"id":2960549,"name":"Garnich"},{"id":2960556,"name":"Frisange"},{"id":2960561,"name":"Fouhren"},{"id":2960563,"name":"Folschette"},{"id":2960564,"name":"Folkendange"},{"id":2960565,"name":"Foetz"},{"id":2960568,"name":"Flaxweiler"},{"id":2960571,"name":"Fischbach"},{"id":2960573,"name":"Fingig"},{"id":2960575,"name":"Findel"},{"id":2960576,"name":"Filsdorf"},{"id":2960577,"name":"Niederfeulen"},{"id":2960583,"name":"Roudenhaff"},{"id":2960584,"name":"Fentange"},{"id":2960586,"name":"Fennange"},{"id":2960588,"name":"Everlange"},{"id":2960589,"name":"Ettelbruck"},{"id":2960590,"name":"Ettelbruck"},{"id":2960592,"name":"Eselborn"},{"id":2960595,"name":"Esch-sur-Sûre"},{"id":2960596,"name":"Esch-sur-Alzette"},{"id":2960597,"name":"Eschette"},{"id":2960598,"name":"Eschdorf"},{"id":2960599,"name":"Canton d'Esch-sur-Alzette"},{"id":2960600,"name":"Ersange"},{"id":2960601,"name":"Erpeldange"},{"id":2960605,"name":"Ernzen"},{"id":2960607,"name":"Ernster"},{"id":2960608,"name":"Ermsdorf"},{"id":2960609,"name":"Eppeldorf"},{"id":2960610,"name":"Enscherange"},{"id":2960611,"name":"Emerange"},{"id":2960613,"name":"Elvange"},{"id":2960614,"name":"Eltz"},{"id":2960615,"name":"Ellange"},{"id":2960616,"name":"Ell"},{"id":2960617,"name":"Eisenborn"},{"id":2960618,"name":"Eischen"},{"id":2960625,"name":"Ehnen"},{"id":2960627,"name":"Ehlerange"},{"id":2960628,"name":"Ehlange"},{"id":2960629,"name":"Canton d'Echternach"},{"id":2960630,"name":"Echternach"},{"id":2960631,"name":"Echternach"},{"id":2960634,"name":"Dudelange"},{"id":2960635,"name":"Dudelange"},{"id":2960636,"name":"Drinklange"},{"id":2960638,"name":"Drauffelt"},{"id":2960641,"name":"Dorscheid"},{"id":2960643,"name":"Doennange"},{"id":2960644,"name":"Doncols"},{"id":2960647,"name":"Dirbach"},{"id":2960648,"name":"Dippach"},{"id":2960649,"name":"Dillingen"},{"id":2960651,"name":"Differdange"},{"id":2960652,"name":"Differdange"},{"id":2960655,"name":"District de Diekirch"},{"id":2960656,"name":"Diekirch"},{"id":2960657,"name":"Diekirch"},{"id":2960659,"name":"Dickweiler"},{"id":2960660,"name":"Derenbach"},{"id":2960665,"name":"Dalheim"},{"id":2960667,"name":"Dahl"},{"id":2960668,"name":"Cruchten"},{"id":2960672,"name":"Crauthem"},{"id":2960673,"name":"Contern"},{"id":2960674,"name":"Consthum"},{"id":2960675,"name":"Consdorf"},{"id":2960676,"name":"Colpach-Haut"},{"id":2960680,"name":"Colmar"},{"id":2960683,"name":"Clervaux"},{"id":2960684,"name":"Clervaux"},{"id":2960687,"name":"Clemency"},{"id":2960691,"name":"Christnach"},{"id":2960692,"name":"Château Faubourg"},{"id":2960694,"name":"Cessange"},{"id":2960696,"name":"Capellen"},{"id":2960697,"name":"Capellen"},{"id":2960699,"name":"Canach"},{"id":2960700,"name":"Calmus"},{"id":2960702,"name":"Buschrodt"},{"id":2960703,"name":"Buschdorf"},{"id":2960704,"name":"Burmerange"},{"id":2960706,"name":"Burden"},{"id":2960718,"name":"Brouch"},{"id":2960720,"name":"Bridel"},{"id":2960721,"name":"Breinert"},{"id":2960722,"name":"Breidweiler"},{"id":2960730,"name":"Brachtenbach"},{"id":2960731,"name":"Boxhorn"},{"id":2960732,"name":"Bous"},{"id":2960734,"name":"Bourscheid"},{"id":2960735,"name":"Bourglinster"},{"id":2960736,"name":"Bour"},{"id":2960737,"name":"Boulaide"},{"id":2960738,"name":"Boudler"},{"id":2960739,"name":"Born"},{"id":2960741,"name":"Bonnevoie"},{"id":2960746,"name":"Bofferdange"},{"id":2960747,"name":"Boevange-sur-Attert"},{"id":2960748,"name":"Boevange"},{"id":2960750,"name":"Bockholtz"},{"id":2960752,"name":"Blumenthal"},{"id":2960754,"name":"Blaschette"},{"id":2960755,"name":"Biwisch"},{"id":2960758,"name":"Bivels"},{"id":2960759,"name":"Bissen"},{"id":2960764,"name":"Bivange"},{"id":2960765,"name":"Binsfeld"},{"id":2960766,"name":"Bilsdorf"},{"id":2960769,"name":"Bigonville"},{"id":2960770,"name":"Bigelbach"},{"id":2960771,"name":"Beyren"},{"id":2960774,"name":"Betzdorf"},{"id":2960775,"name":"Bettendorf"},{"id":2960777,"name":"Bettembourg"},{"id":2960778,"name":"Bettembourg"},{"id":2960779,"name":"Bettel"},{"id":2960780,"name":"Bettborn"},{"id":2960781,"name":"Bettange-sur-Mess"},{"id":2960782,"name":"Bertrange"},{"id":2960784,"name":"Berschbach"},{"id":2960791,"name":"Bergem"},{"id":2960795,"name":"Béreldange"},{"id":2960796,"name":"Berdorf"},{"id":2960797,"name":"Berchem"},{"id":2960799,"name":"Berbourg"},{"id":2960800,"name":"Belvaux"},{"id":2960801,"name":"Belval"},{"id":2960803,"name":"Beidweiler"},{"id":2960806,"name":"Beckerich"},{"id":2960807,"name":"Bech"},{"id":2960809,"name":"Beaufort"},{"id":2960811,"name":"Bavigne"},{"id":2960813,"name":"Bastendorf"},{"id":2960814,"name":"Baschleiden"},{"id":2960815,"name":"Bascharage"},{"id":2960816,"name":"Basbellain"},{"id":2960820,"name":"Asselborn"},{"id":2960822,"name":"Assel"},{"id":2960823,"name":"Aspelt"},{"id":2960827,"name":"Arsdorf"},{"id":2960828,"name":"Ansembourg"},{"id":2960829,"name":"Angelsberg"},{"id":2960832,"name":"Alzingen"},{"id":2960833,"name":"Altwies"},{"id":2960834,"name":"Altrier"},{"id":2960843,"name":"Aciérie"},{"id":2960844,"name":"Abweiler"},{"id":3283390,"name":"Bech-Kleinmacher"},{"id":3285197,"name":"Feulen"},{"id":6693258,"name":"Bascharage"},{"id":6693259,"name":"Clemency"},{"id":6693260,"name":"Dippach"},{"id":6693261,"name":"Garnich"},{"id":6693262,"name":"Hobscheid"},{"id":6693263,"name":"Kehlen"},{"id":6693264,"name":"Koerich"},{"id":6693265,"name":"Kopstal"},{"id":6693266,"name":"Mamer"},{"id":6693267,"name":"Septfontaines"},{"id":6693268,"name":"Steinfort"},{"id":6693269,"name":"Esch-sur-Alzette"},{"id":6693270,"name":"Frisange"},{"id":6693271,"name":"Leudelange"},{"id":6693272,"name":"Mondercange"},{"id":6693273,"name":"Reckange-sur-Mess"},{"id":6693274,"name":"Roeser"},{"id":6693275,"name":"Bertrange"},{"id":6693276,"name":"Contern"},{"id":6693277,"name":"Hesperange"},{"id":6693278,"name":"Niederanven"},{"id":6693279,"name":"Sandweiler"},{"id":6693280,"name":"Schuttrange"},{"id":6693281,"name":"Steinsel"},{"id":6693282,"name":"Strassen"},{"id":6693283,"name":"Walferdange"},{"id":6693284,"name":"Weiler-la-Tour"},{"id":6693286,"name":"Bissen"},{"id":6693287,"name":"Boevange-sur-Attert"},{"id":6693288,"name":"Fischbach"},{"id":6693289,"name":"Heffingen"},{"id":6693290,"name":"Larochette"},{"id":6693291,"name":"Lintgen"},{"id":6693292,"name":"Lorentzweiler"},{"id":6693293,"name":"Mersch"},{"id":6693294,"name":"Nommern"},{"id":6693295,"name":"Tuntange"},{"id":6693296,"name":"Wincrange"},{"id":6693297,"name":"Clervaux"},{"id":6693298,"name":"Consthum"},{"id":6693299,"name":"Heinerscheid"},{"id":6693300,"name":"Hosingen"},{"id":6693301,"name":"Munshausen"},{"id":6693302,"name":"Weiswampach"},{"id":6693305,"name":"Bourscheid"},{"id":6693306,"name":"Ermsdorf"},{"id":6693307,"name":"Erpeldange"},{"id":6693308,"name":"Hoscheid"},{"id":6693309,"name":"Medernach"},{"id":6693311,"name":"Reisdorf"},{"id":6693312,"name":"Schieren"},{"id":6693313,"name":"Beckerich"},{"id":6693314,"name":"Ell"},{"id":6693315,"name":"Rambrouch"},{"id":6693316,"name":"Grosbous"},{"id":6693317,"name":"Redange-sur-Attert"},{"id":6693318,"name":"Saeul"},{"id":6693319,"name":"Useldange"},{"id":6693320,"name":"Vichten"},{"id":6693321,"name":"Wahl"},{"id":6693322,"name":"Boulaide"},{"id":6693323,"name":"Esch-sur-Sûre"},{"id":6693326,"name":"Heiderscheid"},{"id":6693327,"name":"Kautenbach"},{"id":6693328,"name":"Neunhausen"},{"id":6693329,"name":"Wilwerwiltz"},{"id":6693330,"name":"Winseler"},{"id":6693331,"name":"Tandel"},{"id":6693332,"name":"Putscheid"},{"id":6693333,"name":"Vianden"},{"id":6693334,"name":"Beaufort"},{"id":6693335,"name":"Bech"},{"id":6693336,"name":"Berdorf"},{"id":6693337,"name":"Consdorf"},{"id":6693338,"name":"Mompach"},{"id":6693339,"name":"Rosport"},{"id":6693340,"name":"Waldbillig"},{"id":6693341,"name":"Betzdorf"},{"id":6693343,"name":"Flaxweiler"},{"id":6693344,"name":"Junglinster"},{"id":6693345,"name":"Manternach"},{"id":6693346,"name":"Mertert"},{"id":6693347,"name":"Wormeldange"},{"id":6693348,"name":"Bous"},{"id":6693349,"name":"Burmerange"},{"id":6693350,"name":"Dalheim"},{"id":6693351,"name":"Lenningen"},{"id":6693352,"name":"Mondorf-les-Bains"},{"id":6693353,"name":"Schengen"},{"id":6693354,"name":"Remich"},{"id":6693355,"name":"Stadtbredimus"},{"id":6693356,"name":"Waldbredimus"},{"id":6693357,"name":"Wellenstein"},{"id":6696267,"name":"Bollendorf-Pont"}]