[{"id":3573520,"name":"Woodlands"},{"id":3573541,"name":"Waterloo"},{"id":3573576,"name":"Tunapuna"},{"id":3573591,"name":"Republic of Trinidad and Tobago"},{"id":3573596,"name":"Tortuga"},{"id":3573604,"name":"Toco"},{"id":3573606,"name":"Tobago"},{"id":3573638,"name":"Talparo"},{"id":3573643,"name":"Paradise"},{"id":3573645,"name":"Tableland"},{"id":3573650,"name":"Tabaquite"},{"id":3573652,"name":"Success"},{"id":3573665,"name":"Speyside"},{"id":3573681,"name":"Siparia"},{"id":3573703,"name":"Scarborough"},{"id":3573732,"name":"Sangre Grande"},{"id":3573738,"name":"San Fernando"},{"id":3573739,"name":"San Fernando"},{"id":3573764,"name":"Saint Marys"},{"id":3573768,"name":"Saint Margaret"},{"id":3573773,"name":"Saint Joseph"},{"id":3573781,"name":"Saint Helena"},{"id":3573794,"name":"Saint Clair"},{"id":3573804,"name":"Saint Andrew"},{"id":3573819,"name":"Roxborough"},{"id":3573822,"name":"Roussillac"},{"id":3573840,"name":"Rio Claro"},{"id":3573850,"name":"Reform"},{"id":3573854,"name":"Red Hill"},{"id":3573882,"name":"Princes Town"},{"id":3573885,"name":"Preysal"},{"id":3573890,"name":"Port of Spain"},{"id":3573891,"name":"City of Port of Spain"},{"id":3573899,"name":"Point Fortin"},{"id":3573918,"name":"Piparo"},{"id":3573935,"name":"Petit Valley"},{"id":3573957,"name":"Petit Bourg"},{"id":3573965,"name":"Peñal"},{"id":3573972,"name":"Patience Hill"},{"id":3573989,"name":"Paradise"},{"id":3573995,"name":"Palo Seco"},{"id":3574038,"name":"New Grant"},{"id":3574069,"name":"Mucurapo"},{"id":3574081,"name":"Morvant"},{"id":3574087,"name":"Moruga"},{"id":3574103,"name":"Morichal"},{"id":3574104,"name":"Moriah"},{"id":3574116,"name":"Mon Repos"},{"id":3574168,"name":"Matura"},{"id":3574184,"name":"Maraval"},{"id":3574194,"name":"Marabella"},{"id":3574211,"name":"Manahambre"},{"id":3574263,"name":"Lopinot"},{"id":3574309,"name":"Laventille"},{"id":3574323,"name":"La Pastora"},{"id":3574345,"name":"La Finette"},{"id":3574466,"name":"Green Hill"},{"id":3574497,"name":"Gran Couva"},{"id":3574517,"name":"Glamorgan"},{"id":3574524,"name":"Gasparillo"},{"id":3574536,"name":"Fyzabad"},{"id":3574552,"name":"Four Roads"},{"id":3574578,"name":"Exchange"},{"id":3574604,"name":"El Dorado"},{"id":3574632,"name":"Dinsley"},{"id":3574655,"name":"Delaford"},{"id":3574659,"name":"Debe"},{"id":3574671,"name":"Curepe"},{"id":3574689,"name":"Cumuto"},{"id":3574724,"name":"Couva"},{"id":3574729,"name":"Coryal"},{"id":3574738,"name":"Corbeaux Town"},{"id":3574766,"name":"Coco"},{"id":3574773,"name":"Claxton Bay"},{"id":3574794,"name":"Chase Village"},{"id":3574806,"name":"Chaguaramas"},{"id":3574810,"name":"Chaguanas"},{"id":3574874,"name":"Cap-de-Ville"},{"id":3574877,"name":"Caparo"},{"id":3574878,"name":"Cantaro"},{"id":3574888,"name":"Canaan"},{"id":3574928,"name":"Brickfield"},{"id":3574952,"name":"Bon Accord Village"},{"id":3574957,"name":"Boissiere Village"},{"id":3574986,"name":"Black Rock"},{"id":3575039,"name":"Arouca"},{"id":3575051,"name":"Arima"},{"id":3575052,"name":"Arima"},{"id":3575073,"name":"Adelphi"},{"id":7521937,"name":"Chaguanas"},{"id":7521939,"name":"Diego Martin"},{"id":7521940,"name":"Eastern Tobago"},{"id":7521941,"name":"Penal/Debe"},{"id":7521943,"name":"Point Fortin"},{"id":7521944,"name":"Sangre Grande"},{"id":7521945,"name":"Siparia"},{"id":7521947,"name":"Tunapuna/Piarco"}]